test_ransomware-0.1.dist-info/METADATA
test_ransomware-0.1.dist-info/WHEEL
test_ransomware-0.1.dist-info/entry_points.txt
test_ransomware-0.1.dist-info/licenses/LICENSE
ransomware/rlib.pyi
ransomware/core/ransom_note.py
ransomware/core/supervisor.py
ransomware/core/__init__.py
ransomware/core/runtime.py
ransomware/__init__.py
ransomware/utils/arguments.py
ransomware/utils/__init__.py
ransomware/utils/ende.py
ransomware/utils/helptext.py
ransomware/exceptions.py
ransomware/main.py
ransomware/rlib.cpython-312-darwin.so
test_ransomware-0.1.dist-info/RECORD
