Metadata-Version: 2.3
Name: test-ransomware
Version: 0.1
Requires-Dist: maturin
Requires-Dist: argpi
License-File: LICENSE
Summary: Ransomware for Testing purpose
Project-URL: GitHub, https://github.com/d33p0st/looger
